odoo/addons/budget_plan_detail_expense/README.rst
odoo/addons/budget_plan_detail_expense/__init__.py
odoo/addons/budget_plan_detail_expense/__manifest__.py
odoo/addons/budget_plan_detail_expense/hooks.py
odoo/addons/budget_plan_detail_expense/models/__init__.py
odoo/addons/budget_plan_detail_expense/models/account_analytic_dimension.py
odoo/addons/budget_plan_detail_expense/models/hr_expense.py
odoo/addons/budget_plan_detail_expense/readme/CONTRIBUTORS.md
odoo/addons/budget_plan_detail_expense/readme/DESCRIPTION.md
odoo/addons/budget_plan_detail_expense/report/__init__.py
odoo/addons/budget_plan_detail_expense/report/budget_source_fund_report.py
odoo/addons/budget_plan_detail_expense/static/description/icon.png
odoo/addons/budget_plan_detail_expense/static/description/index.html
odoo/addons/budget_plan_detail_expense/tests/__init__.py
odoo/addons/budget_plan_detail_expense/tests/test_budget_plan_detail_expense.py
odoo/addons/budget_plan_detail_expense/views/expense_budget_move.xml
odoo/addons/budget_plan_detail_expense/views/hr_expense_view.xml
odoo_addon_budget_plan_detail_expense-18.0.1.1.3.dist-info/METADATA
odoo_addon_budget_plan_detail_expense-18.0.1.1.3.dist-info/WHEEL
odoo_addon_budget_plan_detail_expense-18.0.1.1.3.dist-info/top_level.txt
odoo_addon_budget_plan_detail_expense-18.0.1.1.3.dist-info/RECORD
